libtool/README_in.md
libtool/build_md.py
libtool/get_imports.py
libtool/libtool_class.py
libtool/tmp_text.py
libtool/up_version.py
libtool/_cmd_argv/cmd.py
libtool/pypi/up_pypi.py
libtool/util/builtins.py
libtool/util/regex.py
libtool-1.1.0.data/scripts/libtool.bat
libtool-1.1.0.dist-info/METADATA
libtool-1.1.0.dist-info/WHEEL
libtool-1.1.0.dist-info/top_level.txt
libtool-1.1.0.dist-info/RECORD
