Metadata-Version: 2.1
Name: libtool
Version: 1.1.0
Summary: Create, version and upload library
Home-page: https://github.com/matan-h/libtool
Author: matan h
Author-email: matan.honig2@gmail.com,
License: MIT
Platform: UNKNOWN
Classifier: Programming Language :: Python :: 3
Classifier: License :: OSI Approved :: MIT License
Classifier: Operating System :: OS Independent
Requires-Python: >=3.7
